lua/class.lua
lua/diagnostic.lua
lua/fibaro.lua
lua/init.lua
lua/json.lua
lua/lfs.lua
lua/mobdebug.lua
lua/net.lua
lua/socket.lua
lua/timers.lua
lua/fibaro/embedui.lua
lua/fibaro/emulator.lua
lua/fibaro/fibaro_api.lua
lua/fibaro/fibaro_funs.lua
lua/fibaro/helper.lua
lua/fibaro/log.lua
lua/fibaro/offline.lua
lua/fibaro/offline_data.lua
lua/fibaro/proxy.lua
lua/fibaro/quickapp.lua
lua/fibaro/tools.lua
lua/fibaro/ui.lua
lua/fibaro/utils.lua
lua/fibaro/lib/aeslua53.lua
lua/fibaro/lib/betterqa.lua
lua/fibaro/lib/eventlib.lua
lua/fibaro/lib/eventmgr.lua
lua/fibaro/lib/markdown.lua
lua/fibaro/lib/qwikchild.lua
lua/fibaro/lib/rpc.lua
lua/fibaro/lib/selectable.lua
lua/fibaro/lib/sha2.lua
lua/fibaro/lib/sourcetrigger.lua
lua/fibaro/tools/backup.lua
lua/fibaro/tools/list.lua
lua/rsrc/PluaHelper.fqa
lua/rsrc/devices.json
plua/__init__.py
plua/api_server.py
plua/cli.py
plua/console.py
plua/engine.py
plua/extensions.py
plua/fastapi_process.py
plua/fibaro_api_endpoints.py
plua/fibaro_api_models.py
plua/generate_typed_fibaro_api.py
plua/lua_bindings.py
plua/path_utils.py
plua/scaffolding.py
plua/sync_socket.py
plua/timers.py
plua/window_manager.py
plua/static/basic_quickapp_template.lua
plua/static/plua_main_page.css
plua/static/plua_main_page.html
plua/static/plua_main_page.js
plua/static/project_config.json
plua/static/quickapp_ui.html
plua/static/vscode_launch_config.json
plua/static/vscode_tasks_config.json
plua-1.2.54.dist-info/licenses/LICENSE
pylib/__init__.py
pylib/filesystem.py
pylib/http_client.py
pylib/mqtt_client.py
pylib/tcp_client.py
pylib/udp_client.py
pylib/websocket_client.py
plua-1.2.54.dist-info/METADATA
plua-1.2.54.dist-info/WHEEL
plua-1.2.54.dist-info/entry_points.txt
plua-1.2.54.dist-info/top_level.txt
plua-1.2.54.dist-info/RECORD
