Metadata-Version: 2.4
Name: plua
Version: 1.2.54
Summary: Python project using Lupa to run Lua scripts with async timer functionality
Author-email: Jan Gabrielsson <jan@gabrielsson.com>
License-Expression: MIT
Project-URL: Homepage, https://github.com/jangabrielsson/plua
Project-URL: Documentation, https://github.com/jangabrielsson/plua#readme
Project-URL: Repository, https://github.com/jangabrielsson/plua
Project-URL: Changelog, https://github.com/jangabrielsson/plua/blob/main/CHANGELOG.md
Project-URL: Issues, https://github.com/jangabrielsson/plua/issues
Requires-Python: >=3.8
License-File: LICENSE
Requires-Dist: lupa>=2.0
Requires-Dist: aiohttp>=3.8.0
Requires-Dist: aiomqtt>=2.0.0
Requires-Dist: fastapi>=0.100.0
Requires-Dist: uvicorn[standard]>=0.23.0
Requires-Dist: websockets>=11.0
Requires-Dist: httpx>=0.24.0
Requires-Dist: requests>=2.28.0
Requires-Dist: prompt_toolkit>=3.0.0
Requires-Dist: rich>=13.0.0
Provides-Extra: dev
Requires-Dist: pytest>=7.0; extra == "dev"
Requires-Dist: pytest-asyncio>=0.21.0; extra == "dev"
Requires-Dist: black>=22.0; extra == "dev"
Requires-Dist: flake8>=5.0; extra == "dev"
Provides-Extra: build
Requires-Dist: nuitka>=2.0.0; extra == "build"
Requires-Dist: psutil>=5.8.0; extra == "build"
Dynamic: license-file
